README.rst
setup.py
PyStratum_MSSQL.egg-info/PKG-INFO
PyStratum_MSSQL.egg-info/SOURCES.txt
PyStratum_MSSQL.egg-info/dependency_links.txt
PyStratum_MSSQL.egg-info/requires.txt
PyStratum_MSSQL.egg-info/top_level.txt
pystratum_mssql/MsSqlConnector.py
pystratum_mssql/MsSqlDataLayer.py
pystratum_mssql/MsSqlDefaultConnector.py
pystratum_mssql/MsSqlMetadataDataLayer.py
pystratum_mssql/__init__.py
pystratum_mssql/backend/MsSqlBackend.py
pystratum_mssql/backend/MsSqlConstantWorker.py
pystratum_mssql/backend/MsSqlRoutineLoaderWorker.py
pystratum_mssql/backend/MsSqlRoutineWrapperGeneratorWorker.py
pystratum_mssql/backend/MsSqlWorker.py
pystratum_mssql/backend/__init__.py
pystratum_mssql/helper/MsSqlDataTypeHelper.py
pystratum_mssql/helper/MsSqlRoutineLoaderHelper.py
pystratum_mssql/helper/__init__.py
pystratum_mssql/wrapper/MsSqlFunctionsWrapper.py
pystratum_mssql/wrapper/MsSqlLogWrapper.py
pystratum_mssql/wrapper/MsSqlNoneWrapper.py
pystratum_mssql/wrapper/MsSqlRow0Wrapper.py
pystratum_mssql/wrapper/MsSqlRow1Wrapper.py
pystratum_mssql/wrapper/MsSqlRowsWithIndexWrapper.py
pystratum_mssql/wrapper/MsSqlRowsWithKeyWrapper.py
pystratum_mssql/wrapper/MsSqlRowsWrapper.py
pystratum_mssql/wrapper/MsSqlSingleton0Wrapper.py
pystratum_mssql/wrapper/MsSqlSingleton1Wrapper.py
pystratum_mssql/wrapper/MsSqlTableWrapper.py
pystratum_mssql/wrapper/MsSqlWrapper.py
pystratum_mssql/wrapper/__init__.py