Metadata-Version: 1.1
Name: PyStratum-MSSQL
Version: 1.0.1
Summary: PyStratum-MSSQL: MS SQL Server Backend
Home-page: https://github.com/DatabaseStratum/py-stratum-mssql
Author: Set Based IT Consultancy
Author-email: info@setbased.nl
License: MIT
Keywords: PyStratum,MS SQL Server
Platform: UNKNOWN
Classifier: Development Status :: 5 - Production/Stable
Classifier: Intended Audience :: Developers
Classifier: Topic :: Software Development :: Build Tools
Classifier: Topic :: Software Development :: Code Generators
Classifier: Topic :: System :: Installation/Setup
Classifier: License :: OSI Approved :: MIT License
Classifier: Programming Language :: Python :: 3
Classifier: Programming Language :: Python :: 3.6
Classifier: Programming Language :: Python :: 3.7
Classifier: Programming Language :: Python :: 3.8
Classifier: Programming Language :: Python :: 3.9
